rosbag_merge/__init__.py
rosbag_merge/bag_stream.py
rosbag_merge/main.py
rosbag_merge/deprecated/csv_merge.py
rosbag_merge/deprecated/merge_bags.py
rosbag_merge/deprecated/rosbag_to_csv.py
rosbag_merge-0.1.6.dist-info/METADATA
rosbag_merge-0.1.6.dist-info/WHEEL
rosbag_merge-0.1.6.dist-info/entry_points.txt
rosbag_merge-0.1.6.dist-info/licenses/LICENSE
rosbag_merge-0.1.6.dist-info/RECORD
