Metadata-Version: 2.3
Name: rosbag_merge
Version: 0.1.6
Summary: A gathering of tools for merging rosbags and saving their topic information to csv.
Project-URL: Homepage, https://github.com/1hada/rosbag-merge/
Project-URL: Bug Tracker, https://github.com/1hada/rosbag-merge/issues/
Author-email: Jonathan Sanabria <jonsanria@gmail.com>
License:                                  Apache License
License-File: LICENSE
Classifier: Intended Audience :: Developers
Classifier: Intended Audience :: System Administrators
Classifier: License :: OSI Approved :: Apache Software License
Classifier: Operating System :: OS Independent
Classifier: Programming Language :: Python :: 3
Requires-Python: >=3.7
Requires-Dist: icecream
Requires-Dist: rosbags
Requires-Dist: tqdm
